setup.py
src/toil_signalAlign.egg-info/PKG-INFO
src/toil_signalAlign.egg-info/SOURCES.txt
src/toil_signalAlign.egg-info/dependency_links.txt
src/toil_signalAlign.egg-info/entry_points.txt
src/toil_signalAlign.egg-info/requires.txt
src/toil_signalAlign.egg-info/top_level.txt
src/toil_signalalign/__init__.py
src/toil_signalalign/minionSample.py
src/toil_signalalign/toil_signalalign_pipeline.py