Metadata-Version: 1.0
Name: toil-signalAlign
Version: 0.1.3
Summary: Toil script for signal-level analysis of ONT data
Home-page: https://github.com/ArtRand/toil-signalAlign
Author: Art Rand
Author-email: arand@soe.ucsc.edu
License: UNKNOWN
Platform: UNKNOWN
